[
  {
    "age": "0-5",
    "persons": 1355867,
    "males": 655808,
    "females": 700059
  },
  {
    "age": "5-10",
    "persons": 1452854,
    "males": 761656,
    "females": 691198
  },
  {
    "age": "10-15",
    "persons": 1350321,
    "males": 670539,
    "females": 679782
  },
  {
    "age": "15-20",
    "persons": 852389,
    "males": 428409,
    "females": 423980
  },
  {
    "age": "20-25",
    "persons": 894027,
    "males": 405799,
    "females": 488228
  },
  {
    "age": "25-30",
    "persons": 1051503,
    "males": 523613,
    "females": 527890
  },
  {
    "age": "30-35",
    "persons": 1072226,
    "males": 542213,
    "females": 530013
  },
  {
    "age": "35-40",
    "persons": 628589,
    "males": 312413,
    "females": 316176
  },
  {
    "age": "40-45",
    "persons": 818675,
    "males": 425713,
    "females": 392962
  },
  {
    "age": "45-50",
    "persons": 357058,
    "males": 200841,
    "females": 156217
  },
  {
    "age": "50-55",
    "persons": 588550,
    "males": 299341,
    "females": 289209
  },
  {
    "age": "55-60",
    "persons": 168158,
    "males": 97034,
    "females": 71064
  },
  {
    "age": "60 and over",
    "persons": 307011,
    "males": 107496,
    "females": 199519
  },
  {
    "age": "Total",
    "persons": 11141142,
    "males": 5673629,
    "females": 5467513
  }
]